Metadata-Version: 1.1
Name: kubernetify
Version: 1
Summary: takes a string and kubernetifies it
Home-page: https://github.com/gregford117/kubernetify
Author: Greg Ford
Author-email: gregford117@live.com
License: MIT
Download-URL: https://github.com/gregford117/kubernetify/archive/v_1.tar.gz
Keywords: KUBERNETES,KUBERNETIFY
Platform: UNKNOWN
Classifier: Development Status :: 3 - Alpha
Classifier: Intended Audience :: Developers
Classifier: Topic :: Software Development :: Build Tools
Classifier: License :: OSI Approved :: MIT License
Classifier: Programming Language :: Python :: 3
Classifier: Programming Language :: Python :: 3.4
Classifier: Programming Language :: Python :: 3.5
Classifier: Programming Language :: Python :: 3.6
Classifier: Programming Language :: Python :: 3.7
